timeStampBySamuwa/__init__.py
timeStampBySamuwa/timeStampBySamuwa.py
timeStampBySamuwa-0.0.1.dist-info/METADATA
timeStampBySamuwa-0.0.1.dist-info/WHEEL
timeStampBySamuwa-0.0.1.dist-info/top_level.txt
timeStampBySamuwa-0.0.1.dist-info/RECORD
