Metadata-Version: 2.1
Name: timeStampBySamuwa
Version: 0.0.1
Summary: Generate Time Stamp String
Home-page: UNKNOWN
Author: Samuwa
Author-email: samuel.wainberg@gmail.com
License: UNKNOWN
Keywords: python,time stamp
Platform: UNKNOWN
Classifier: Development Status :: 1 - Planning
Classifier: Intended Audience :: Developers
Classifier: Programming Language :: Python :: 3
Classifier: Operating System :: Unix
Classifier: Operating System :: MacOS :: MacOS X
Classifier: Operating System :: Microsoft :: Windows
Requires-Dist: datetime
